epipackpy/__init__.py
epipackpy/_version.py
epipackpy/data/__init__.py
epipackpy/data/dataload.py
epipackpy/model/PEIVI.py
epipackpy/model/PEIVI_mapping.py
epipackpy/model/__init__.py
epipackpy/model/classifier.py
epipackpy/model/global_oor.py
epipackpy/model/local_oor.py
epipackpy/model/loss.py
epipackpy/model/net.py
epipackpy/model/peak_model.py
epipackpy/model/utils.py
epipackpy-1.0.1.dist-info/LICENSE.txt
epipackpy-1.0.1.dist-info/METADATA
epipackpy-1.0.1.dist-info/WHEEL
epipackpy-1.0.1.dist-info/top_level.txt
epipackpy-1.0.1.dist-info/RECORD
