Metadata-Version: 2.1
Name: epipackpy
Version: 1.0.1
Summary: EpiPack: scATAC-seq integration, reference mapping and cell type annotation
Home-page: https://github.com/ZhangLabGT/EpiPack
Author: Yuqi Cheng
Author-email: ycheng430@gatech.edu
License: MIT
Requires-Python: >=3.8, <3.12
License-File: LICENSE.txt
Requires-Dist: numpy >=1.17.0
Requires-Dist: pandas <2.1.2,>=1.0
Requires-Dist: scipy <2.0.0,>=1.4
Requires-Dist: scikit-learn <2.0.0,>=0.23
Requires-Dist: tqdm >=4.62
Requires-Dist: typing-extensions
Requires-Dist: torch >=2.0
Requires-Dist: polars >=0.19
Requires-Dist: pyarrow >=14.0
Requires-Dist: pybiomart >=0.2.0
Requires-Dist: pyranges
Requires-Dist: seaborn >=0.12
